{
  "product": {
    "productId": 1005002525279564,
    "title": "MOES Smart ZigBee Bluetooth Mesh Brightness Thermometer Sensor Light Temperature Humidity Detector Tuya Smart App Control",
    "description": "",
    "reference": "Bluetooth Hub",
    "salePrice": "16.28",
    "discount": "",
    "currency": "USD",
    "originalPrice": "27.13",
    "quantity": "11728",
    "image": "https://ae01.alicdn.com/kf/Sb72e64cfe25c43e1a99e1fb3f29b025c1/MOES-Smart-ZigBee-Bluetooth-Mesh-Brightness-Thermometer-Sensor-Light-Temperature-Humidity-Detector-Tuya-Smart-App-Control.jpg_Q90.jpg_.webp",
    "storeInfo": {
      "name": "MOES Online Store",
      "url": "https://www.aliexpress.com/store/5492026",
      "storeNumber": "5492026",
      "rating": "95.6%",
      "followers": "228518"
    },
    "ratings": {
      "totalStar": 5,
      "averageStar": "5.0",
      "totalStarCount": "2"
    }
  }
}