{
    "product": {
        "linkId": "sonoff-zbminil2-extreme-zigbee-smart-switch-no-neutral-required",
        "productId": "SONOFFZBMINIL2Zigbee 3.039.5X32X18.4mmPC V0100-240V ~ 56/60Hz 6A Max100-240V ~ 56/60Hz 6A Max",
        "title": "SONOFF ZBMINI Extreme Zigbee Smart Switch ZBMINIL2 (No Neutral Required)",
        "description": "",
        "productNew": "",
        "minsalePrice": "",
        "maxsalePrice": "$13.99$119.90$89.90$19.90$24.90$8.49$9.49$8.49$13.99$119.90$89.90$12.99$13.49$15.99$16.99$19.99$19.90$1.99$5.99$4.99$43.90$9.99$9.90$13.99",
        "discount": "",
        "originalPrice": "$13.99$119.90$89.90$19.90$24.90$8.49$9.49$8.49$13.99$119.90$89.90$12.99$13.49$15.99$16.99$19.99$19.90$1.99$5.99$4.99$43.90$9.99$9.90$13.99",
        "quantity": 0,
        "available": "",
        "supply_date": null,
        "image": [],
        "ratings": {
            "totalStar": "5",
            "averageStar": "0",
            "totalStarCount": "0"
        }
    }
}